PillowZhongwenWendang/README.md
PillowZhongwenWendang/__init__.py
PillowZhongwenWendang/__main__.py
PillowZhongwenWendang/file.epub
PillowZhongwenWendang/index.html
PillowZhongwenWendang/css/__init__.py
PillowZhongwenWendang/css/annotations.css
PillowZhongwenWendang/css/main.css
PillowZhongwenWendang/css/normalize.css
PillowZhongwenWendang/css/popup.css
PillowZhongwenWendang/font/__init__.py
PillowZhongwenWendang/font/fontello.eot
PillowZhongwenWendang/font/fontello.svg
PillowZhongwenWendang/font/fontello.ttf
PillowZhongwenWendang/font/fontello.woff
PillowZhongwenWendang/img/__init__.py
PillowZhongwenWendang/img/annotator-glyph-sprite.png
PillowZhongwenWendang/img/annotator-icon-sprite.png
PillowZhongwenWendang/img/apple-touch-icon.png
PillowZhongwenWendang/img/cancelfullscreen.png
PillowZhongwenWendang/img/close.png
PillowZhongwenWendang/img/fullscreen.png
PillowZhongwenWendang/img/loader.gif
PillowZhongwenWendang/img/menu-icon.png
PillowZhongwenWendang/img/save.png
PillowZhongwenWendang/img/saved.png
PillowZhongwenWendang/img/settings-s.png
PillowZhongwenWendang/img/settings.png
PillowZhongwenWendang/img/star.png
PillowZhongwenWendang/js/__init__.py
PillowZhongwenWendang/js/epub.js
PillowZhongwenWendang/js/epub.min.js
PillowZhongwenWendang/js/epub.min.map
PillowZhongwenWendang/js/hooks.min.js
PillowZhongwenWendang/js/hooks.min.map
PillowZhongwenWendang/js/reader.js
PillowZhongwenWendang/js/reader.js.map
PillowZhongwenWendang/js/reader.min.js
PillowZhongwenWendang/js/reader.min.map
PillowZhongwenWendang/js/hooks/__init__.py
PillowZhongwenWendang/js/hooks/extensions/__init__.py
PillowZhongwenWendang/js/hooks/extensions/highlight.js
PillowZhongwenWendang/js/libs/__init__.py
PillowZhongwenWendang/js/libs/jquery.min.js
PillowZhongwenWendang/js/libs/localforage.min.js
PillowZhongwenWendang/js/libs/screenfull.js
PillowZhongwenWendang/js/libs/screenfull.min.js
PillowZhongwenWendang/js/libs/zip.min.js
PillowZhongwenWendang/js/plugins/__init__.py
pillow_zhongwen_wendang-2024.3.2.0.dist-info/METADATA
pillow_zhongwen_wendang-2024.3.2.0.dist-info/WHEEL
pillow_zhongwen_wendang-2024.3.2.0.dist-info/entry_points.txt
pillow_zhongwen_wendang-2024.3.2.0.dist-info/top_level.txt
pillow_zhongwen_wendang-2024.3.2.0.dist-info/RECORD
